hondex/__init__.py
hondex/game_logic.py
hondex/profile.py
hondex_arch/__init__.py
hondex_arch/baseDataclass.py
hondex_arch/baseDataclassMeta.py
hondex_model/battlesuit.py
hondex_model/character.py
hondex_model/stigmataSet.py
hondex_scrap/__init__.py
hondex_scrap/bsScrapper.py
hondex_scrap/charScrapper.py
hondex_scrap/stigScrapper.py
honkaidex-0.3.2.dist-info/LICENSE
honkaidex-0.3.2.dist-info/METADATA
honkaidex-0.3.2.dist-info/WHEEL
honkaidex-0.3.2.dist-info/top_level.txt
honkaidex-0.3.2.dist-info/RECORD
